pyrealm/__init__.py
pyrealm/constants/__init__.py
pyrealm/constants/base.py
pyrealm/constants/competition_const.py
pyrealm/constants/core_const.py
pyrealm/constants/isotope_const.py
pyrealm/constants/phenology_const.py
pyrealm/constants/pmodel_const.py
pyrealm/constants/tmodel_const.py
pyrealm/constants/two_leaf.py
pyrealm/core/__init__.py
pyrealm/core/bounds.py
pyrealm/core/calendar.py
pyrealm/core/experimental.py
pyrealm/core/hygro.py
pyrealm/core/pressure.py
pyrealm/core/solar.py
pyrealm/core/time_series.py
pyrealm/core/utilities.py
pyrealm/core/water.py
pyrealm/demography/__init__.py
pyrealm/demography/canopy.py
pyrealm/demography/community.py
pyrealm/demography/core.py
pyrealm/demography/crown.py
pyrealm/demography/flora.py
pyrealm/demography/tmodel.py
pyrealm/phenology/__init__.py
pyrealm/phenology/fapar_limitation.py
pyrealm/pmodel/__init__.py
pyrealm/pmodel/acclimation.py
pyrealm/pmodel/arrhenius.py
pyrealm/pmodel/competition.py
pyrealm/pmodel/functions.py
pyrealm/pmodel/isotopes.py
pyrealm/pmodel/jmax_limitation.py
pyrealm/pmodel/optimal_chi.py
pyrealm/pmodel/pmodel.py
pyrealm/pmodel/pmodel_environment.py
pyrealm/pmodel/quantum_yield.py
pyrealm/pmodel/two_leaf.py
pyrealm/splash/__init__.py
pyrealm/splash/evap.py
pyrealm/splash/solar.py
pyrealm/splash/splash.py
pyrealm-2.0.0.dist-info/METADATA
pyrealm-2.0.0.dist-info/WHEEL
pyrealm-2.0.0.dist-info/licenses/LICENSE
pyrealm-2.0.0.dist-info/RECORD
