Metadata-Version: 2.4
Name: pyrealm
Version: 2.0.0
Summary: Python tools for modelling plant productivity and demography.
License-Expression: MIT
License-File: LICENSE
Keywords: gross primary productivity,demography,eco-evolutionary optimality
Author: David Orme
Author-email: d.orme@imperial.ac.uk
Maintainer: David Orme
Maintainer-email: d.orme@imperial.ac.uk
Requires-Python: >=3.11
Classifier: Programming Language :: Python :: 3
Classifier: License :: OSI Approved :: MIT License
Classifier: Operating System :: OS Independent
Classifier: Topic :: Scientific/Engineering
Classifier: Intended Audience :: Science/Research
Classifier: Development Status :: 4 - Beta
Requires-Dist: dacite (>1.6.0)
Requires-Dist: marshmallow (>=3.22.0)
Requires-Dist: marshmallow-dataclass (>=8.7.0)
Requires-Dist: numpy (>=2.1)
Requires-Dist: pandas (>=2.2.2)
Requires-Dist: scipy (>=1.7.3)
Requires-Dist: tabulate (>=0.8.10)
Project-URL: Homepage, https://pyrealm.readthedocs.io/
Project-URL: Repository, https://github.com/ImperialCollegeLondon/pyrealm
